{"offset":0,"limit":8,"endOfRecords":false,"count":10406,"results":[{"key":209892860,"nameKey":115247104,"datasetKey":"fab88965-e69d-4491-a04d-e3198b626e52","parentKey":102485135,"parent":"Organismal metagenomes","species":"Wildlife metagenome","speciesKey":209892860,"scientificName":"wildlife metagenome","canonicalName":"Wildlife metagenome","authorship":"","nameType":"SCIENTIFIC","taxonomicStatus":"ACCEPTED","rank":"SPECIES","origin":"SOURCE","numDescendants":0,"numOccurrences":0,"taxonID":"2689586","habitats":[],"nomenclaturalStatus":[],"threatStatuses":[],"descriptions":[],"vernacularNames":[],"synonym":false,"higherClassificationMap":{"102485135":"Organismal metagenomes"}},{"key":209724642,"datasetKey":"6b6b2923-0a10-4708-b170-5b7c611aceef","parentKey":177592058,"parent":"Organismal metagenomes","species":"Wildlife metagenome","speciesKey":209724642,"scientificName":"wildlife metagenome","canonicalName":"Wildlife metagenome","nameType":"SCIENTIFIC","taxonomicStatus":"ACCEPTED","rank":"SPECIES","origin":"SOURCE","numDescendants":0,"numOccurrences":0,"taxonID":"2689586","habitats":[],"nomenclaturalStatus":[],"threatStatuses":[],"descriptions":[],"vernacularNames":[],"synonym":false,"higherClassificationMap":{"177592058":"Organismal metagenomes"}},{"key":165447378,"datasetKey":"cbb6498e-8927-405a-916b-576d00a6289b","parentKey":324728115,"parent":"Clossiana","kingdom":"Animalia","phylum":"Arthropoda","order":"Lepidoptera","family":"Nymphalidae","genus":"Clossiana","species":"Clossiana improba acrocnema","kingdomKey":165236969,"phylumKey":324719775,"classKey":324722440,"orderKey":324723865,"familyKey":324727829,"genusKey":324728115,"speciesKey":165447378,"scientificName":"Clossiana improba subsp. acrocnema U.S.Fish & Wildlife, 2018","canonicalName":"Clossiana improba acrocnema","authorship":"U.S. Fish and Wildlife, 2018","nameType":"SCIENTIFIC","taxonomicStatus":"ACCEPTED","rank":"SPECIES","origin":"SOURCE","numDescendants":0,"numOccurrences":0,"taxonID":"12547991","habitats":[],"nomenclaturalStatus":[],"threatStatuses":[],"descriptions":[{"description":"The Uncompahgre fritillary butterfly (Clossiana improba acrocnema) is a species of butterfly in the Order Lepidoptera: Family Nymphalidae that is endemic to Colorado, USA.U.S. Fish and Wildlife Service (2018). Uncompahgre Fritillary Butterfly (Clossiana improba acrocnema) 5-Year Review: Summary and Evaluation. Western Slope Office, Colorado Ecological Services, Grand Junction, Colorado. Discovered in the summer of 1978, the Uncompahgre fritillary was first described as a subspecies of Boloria improba, commonly known as the dingy fritillaryScott, J.A. 1986. The butterflies of North America - A natural history and field guide. Stanford University Press, Stanford, CA, USA. 583 pp. but further genetic data supported classifying them as a full species.Gall, L.F., and F.A.H. Sperling. 1980. A new high altitude species of Boloria from southwestern Colorado (Nymphalidae), with a discussion of phonetics and hierarchical decisions. J. Lepidopterists's Soc. 34:230-252."},{"description":"The Uncompahgre fritillary was first found above tree-line at Uncompahgre Peak, located in Hinsdale County, Colorado, USA by Larry Gall, Felix Sperling, Scott Graham, Kathleen Shaw, and Wendy Roberts working out of the Rocky Mountain Biological Laboratory. A few years following, another population was found at Redcloud Peak, about 10 miles south of Uncompahgre Peak. The Uncompahgre fritillary butterfly was discovered in 1978 below Uncompahgre Peak, Colorado, USA The species is endemic to the northern San Juan Mountains and the southern Sawatch Range in parts of Gunnison County, Hinsdale County, and Chaffee County of southwestern Colorado, USA and has one of the smallest known ranges of all North American butterflies.Fish and Wildlife Service. 1994. Uncompahgre Fritillary Butterfly Recovery Plan. Denver, Colorado. 20 pp. Since their discovery, small populations of Uncompahgre fritillaries have been discovered at 9 other locations within this region and are monitored annually. Their closest genetic relative is Clossiana improba harryi which has only been found within the Wind River Mountains in Wyoming.Alexander, K.D. and A.G. Keck. 2018. Uncompahgre Fritillary Butterfly Monitoring, Inventory, and Mapping: 2017 Report and Status. 28 pages. Other similar looking species of butterflies are found within these habitats including the Varied checkerspot (Euphydryas anicia), Frieja fritillary (Clossiana frieja), and Arctic fritillary (Clossiana chariclea). The habitat characteristics of these butterflies include alpine tundra environments above tree-line (3800-4200m above sea level) that are northeast facing sloped meadows containing moderate amounts of moisture throughout the year, mostly from winter snowpack and rainfall during monsoon seasons. Host plant Snow willow (Salix nivalis) is the host plant of the Uncompahgre fritillary butterfly. The Uncompahgre fritillary is a specialist species regarding their larval food plant and egg-laying site. They can be found in habitats containing patches of their host plant, snow willow (Salix reticulata spp. nivalis), a dwarf willow that is structurally similar to the Arctic willow (Salix arctica). Adult Uncompahgre fritillary butterfly resting on a rock in the San Juan Mountains of Colorado."},{"description":"Female adult butterflies lay their eggs individually on snow willow stems and leaves around the middle of July and they don't hatch until numerous weeks later.Scott, James A. (1984) The Life History and Ecology of an alpine relict, Boloria improba acrocnema (Lepidoptera: Nymphalidae), illustrating a new mathematical population census method. Papilio (2). The eggs are tan in color and once hatched, the larvae will then feed on snow willow leaves throughout their biennial life cycle and overwinter under the snow until they emerge the following spring and molt. The adult butterflies are small with a fuzzy, dark brown to black body and brown-black antennae. The males and females are differentiated by the females wings being slightly lighter in color than the males.Gall, L.F. 1983. Uncompahgre fritillary butterfly. Pages 477—479 in The IUCN Invertebrate Red Data Book. S.M. Wells, R.M. Pyle, N.M. Collins, eds. International Union for Conservation of Nature and Natural Resources, Gland, Switzerland. 632 pp. Their wingspan is approximately 1 inch wide and their wings are multi-colored containing distinct patterns of tan, orange, brown, and black with a distinct triangular shape emerging on the dorsal and ventral wing. As adult butterflies, the Uncompahgre fritillaries are only in flight for a few weeks during the summer season, emerging following the snow melt at these high elevation mountain peak. They can be seen on wing starting in late-June to early-July and are considered weak fliers that require full sunlight with little to no wind in order to fly and are considered a philopatric species."},{"description":"Population decline Mark-recapture methods completed within a decade of their discovery showed low population estimates at Uncompahgre Peak and Redcloud Peak. The Uncompahgre fritillary was thought to be on the edge of extinction and was added to the Endangered Species List in 1991. Since then, early monitoring programs have found a number of additional populations in the San Juan Mountains but the small numbers detected at each of these locations remain inadequate for delisting. Predicted threats to this species and alpine tundra ecosystems include: grazing, illegal collection, recreation, and climate change, with an additional threat is the possibility of low genetic variability between the known butterfly populations. The impacts of global climate change pose concerns to this species and alpine environments overall. Alpine environments are the coldest locations where pollinator species can still occur but the sensitive species of plants, insects, and animals found within these ecosystems might not have the ability to adapt to changes in temperatures and precipitation patterns.Inouye, D. W. (2020). Effects of climate change on alpine plants and their pollinators. Annals of the New York Academy of Sciences, 1469(1), 26–37. http://doi.org/10.1111/nyas.14104. Recovery efforts The Uncompahgre fritillary butterfly is still listed as Federally Endangered by the U.S. Fish and Wildlife Service and the recovery plan prioritizes actions to better understand the reasons for their low population estimates and to prevent this species from extinction. Their public locations at Uncompahgre Peak and Redcloud Peak are monitored annually by the Bureau of Land Management, U.S. Forest Service, and Colorado Parks and Wildlife to estimate changes in population sizes, as well as to understand more about this species' habitat. Management efforts carried out by these agencies have restricted grazing livestock on these particular slopes, rerouted hiking trails, and installed signage regarding the status of this species at the trailheads of these popular hiking locations. The specialist habitat requirements and small distribution of the Uncompahgre fritillary butterfly make it a useful indicator of the future impacts of climate change could have on alpine ecosystem health and structure.Seidl, A. L. 1999. Population demographics and the conservation status of the Uncompahgre fritillary Boloria acrocnema (Nymphalidae). Journal of the Lepidopterists’ Society 53:32-36. Efforts to preserve this species continue to prevent illegal collection and monitor population numbers, habitat quality, and environmental pressures that future populations could encounter."}],"vernacularNames":[],"synonym":false,"higherClassificationMap":{"165236969":"Animalia","324719775":"Arthropoda","324722440":"Insecta","324723865":"Lepidoptera","324727829":"Nymphalidae","324728115":"Clossiana"},"class":"Insecta"},{"key":165763627,"datasetKey":"cbb6498e-8927-405a-916b-576d00a6289b","parentKey":165763625,"parent":"Velarifictorus","genus":"Velarifictorus","species":"Velarifictorus micado","genusKey":165763625,"speciesKey":165763627,"scientificName":"Velarifictorus micado (Saussure, 1877)","canonicalName":"Velarifictorus micado","authorship":"(Saussure, 1877)","nameType":"SCIENTIFIC","taxonomicStatus":"ACCEPTED","rank":"SPECIES","origin":"SOURCE","numDescendants":0,"numOccurrences":0,"taxonID":"56280233","habitats":[],"nomenclaturalStatus":[],"threatStatuses":[],"descriptions":[{"description":"The Japanese burrowing cricket (Velarifictorus micado) is a cricket in the subfamily Gryllinae (family Gryllidae)bugguide.net Velarifictorus micado species information.Integrated Taxonomic Information System (ITIS) and tribe Modicogryllini. It is found throughout South Asia, along with an introduced population in the United States. It was first reported in the US in 1959, likely as overwintering eggs in the soil of imported plants, and has since spread all throughout the eastern half of the country. Velarifictorus micado front.jpg|''V. micado'' front File:Velarifictorus micado-paralyzed dorsal.jpg|paralyzed by a wasp - dorsal [https://wildlifeprairiepark.org/ Wildlife Prairie Park] File:Velarifictorus micado paralyzed ventral.jpg|paralyzed by a wasp - ventral [https://wildlifeprairiepark.org/ Wildlife Prairie Park] Velarifictorus micado singing in Hyogo.webm|''V. micado'' song"}],"vernacularNames":[],"synonym":false,"higherClassificationMap":{"165763625":"Velarifictorus"}},{"key":165634084,"datasetKey":"cbb6498e-8927-405a-916b-576d00a6289b","parentKey":165634072,"parent":"Callicarpa","genus":"Callicarpa","species":"Callicarpa tomentosa","genusKey":165634072,"speciesKey":165634084,"scientificName":"Callicarpa tomentosa (L.) L.","canonicalName":"Callicarpa tomentosa","authorship":"(L.) L.","nameType":"SCIENTIFIC","taxonomicStatus":"ACCEPTED","rank":"SPECIES","origin":"SOURCE","numDescendants":0,"numOccurrences":0,"taxonID":"16938223","habitats":[],"nomenclaturalStatus":[],"threatStatuses":[],"descriptions":[{"description":"Callicarpa tomentosa is a species of beautyberry plant in the family Lamiaceae. It is found in Western Ghats of India and Sri Lanka. It is a small tree with about 5m tall. Leaves simple, opposite; elliptic to broadly elliptic; apex acute or acuminate. Purplish flowers show branched axillary cymes. Fruit is 3-4 seeded globose drupe. Fruits provide food for wildlife. They are sometimes used to make herbal medicine. The leaves are also food for wildlife.Pharmcographia indica The leaf is know being used as a wick to light a oil lamp."},{"description":"Hindi - Pandavara Batti (Pandav's Torch) Tamil - Vettilai-pattai Malayalam - Thin perivellam, thiriperivelam Kannada - Rishipathiri, Arthigida, Pandavara Batti"}],"vernacularNames":[],"synonym":false,"higherClassificationMap":{"165634072":"Callicarpa"}},{"key":165479797,"datasetKey":"cbb6498e-8927-405a-916b-576d00a6289b","species":"Paralabrax nebulifer","speciesKey":165479797,"scientificName":"Paralabrax nebulifer (Girard, 1854)","canonicalName":"Paralabrax nebulifer","authorship":"(Girard, 1854)","nameType":"SCIENTIFIC","taxonomicStatus":"ACCEPTED","rank":"SPECIES","origin":"SOURCE","numDescendants":0,"numOccurrences":0,"taxonID":"24080449","habitats":[],"nomenclaturalStatus":[],"threatStatuses":[],"descriptions":[{"description":"The barred sand bass, Paralabrax nebulifer, is a species of fish in the family Serranidae, the sea basses and groupers. It is native to California and Baja California, where it lives in the coastal waters of the eastern Pacific Ocean."},{"description":"This species can reach a length of 67.0 cm and a weight of 6.0 kg. The body is elongated and compressed. It is gray-white in color with dark vertical bars and a whitish belly. It has a large mouth and a slightly protruding lower jaw. Similar species include the spotted sand bass (P. maculatofasciatus), which can be distinguished by small spots all along the body. The barred and spotted sand bass have an elongated third dorsal spine, distinguishing them from the similar kelp bass (P. clathratus), which has dorsal spines of equal length.California Marine Sportfish Identification: Sea Bass. California Department of Fish and Wildlife. 2018."},{"description":"Barred sand bass occur from Santa Cruz, California to Magdalena Bay in Baja California Sur."},{"description":"This species lives in shallow waters up to 600 feet deep. It is most commonly caught in 60 to 90 feet of water. It lives on sandy bottoms. The barred sand bass eats other fish, especially plainfin midshipman, and some invertebrates. Juveniles eat many types of small invertebrates and small fish. The species forms spawning aggregations in the warmer months and is a pelagic spawner, releasing eggs freely into the water. Like other species of genus Paralabrax, the barred sand bass can change sex, with individuals turning from female to male as they age and grow larger, but most do not.Baca-Hovey, C. and L. D. Cooper. Reproductive biology of the barred sand bass (Paralabrax nebulifer). Southern California Coastal Water Research Project 1999-2000 Annual Report. This is a popular sport fish in Southern California. Population studies have been performed by the California Department of Fish and Wildlife.Barred Sand Bass Spawning Movements and Habitat Characterization. California Department of Fish and Wildlife. Populations are stable, likely due to recreational fishing regulations and a ban on commercial fishing of the species. It may also benefit from marine protected areas along the California coast."}],"vernacularNames":[],"synonym":false,"higherClassificationMap":{}},{"key":165756612,"datasetKey":"cbb6498e-8927-405a-916b-576d00a6289b","parentKey":165756602,"parent":"Thelypodium","genus":"Thelypodium","species":"Thelypodium howellii","genusKey":165756602,"speciesKey":165756612,"scientificName":"Thelypodium howellii S.Wats.","canonicalName":"Thelypodium howellii","authorship":"S. Wats.","nameType":"SCIENTIFIC","taxonomicStatus":"ACCEPTED","rank":"SPECIES","origin":"SOURCE","numDescendants":0,"numOccurrences":0,"taxonID":"11802514","habitats":[],"nomenclaturalStatus":[],"threatStatuses":[],"descriptions":[{"description":"Thelypodium howellii, the Howell's thelypody or Howell's thelypodium, is a rare plant of the Western United States. It is endemic to a relatively small area on the borders of three western States: Oregon, Nevada, and California."},{"description":"The Thelypodium howellii plant is biennial. It is often somewhat hairy, especially near the base, but may be hairless and waxy in texture. It produces a slender, branching, erect stem up to 70 centimeters tall. The leaves are mostly located in a rosette around the base. Leaves located higher on the stem may have clasping bases. The inflorescence is a raceme of widely spaced flowers with greenish white or purplish sepals and pale blue or purple, spoon-shaped petals. The fruit is a silique up to 4.5 centimeters long containing plump brown seeds. Subspecies Thelypodium howellii subsp. howellii Jepson Manual treatment for Thelypodium howellii subsp. howellii Thelypodium howellii subsp. spectabalis - Howell's spectacular thelypody."},{"description":"This plant is endemic to a small area stretching from north-eastern Oregon to north-eastern California. It lives in alkaline or adobe meadows and seeps, river valleys and moist plains in Great Basin sagebrush scrub. The fire ecology of this plant is not known at present."},{"description":"U.S. Forest Service Pacific Southwest Region Sensitive Species. California Native Plant Society List 1B.2. NatureServe California State Rank: S2.2; Global Rank: G2 Oregon Department of Fish and Wildlife Endangered. The Oregon Department of Fish and Wildlife's Conservation Strategy website reports that a large portion of this species' habitat has been converted to agricultural land, and its numbers are being limited by competition with invasive weeds, changes in hydrology, pressure from cattle grazing, and mowing in preparation for growing season."},{"description":"Howell's thelypody flowers from May to July. Var. spectabilis, known only from Malheur Co., Oregon, is larger than var. howellii, has larger, more strongly purple flowers, and is a federally listed species."}],"vernacularNames":[],"synonym":false,"higherClassificationMap":{"165756602":"Thelypodium"}},{"key":165693670,"datasetKey":"cbb6498e-8927-405a-916b-576d00a6289b","parentKey":165693667,"parent":"Lewinia","genus":"Lewinia","species":"Lewinia pectoralis","genusKey":165693667,"speciesKey":165693670,"scientificName":"Lewinia pectoralis (Temminck, 1831)","canonicalName":"Lewinia pectoralis","authorship":"(Temminck, 1831)","nameType":"SCIENTIFIC","taxonomicStatus":"ACCEPTED","rank":"SPECIES","origin":"SOURCE","numDescendants":0,"numOccurrences":0,"taxonID":"12434418","habitats":[],"nomenclaturalStatus":[],"threatStatuses":[],"descriptions":[{"description":"Lewin's rail (Lewinia pectoralis) is a species of bird in the family Rallidae. It is found in Australia, Wallacea, and New Guinea. Lewin's rail is also known as the water rail, Lewin's water rail, Lewin's grind rail, slate-breasted rail, slate-breasted water rail, pectoral rail, pectoral water rail, short-toed rail and short-toed water rail. Its natural habitat is subtropical or tropical moist lowland forests.Lewin's Rail Details"},{"description":"Eight subspecies have been described: L. p. exsul (Hartert, 1898) – Flores, Wallacea New Guinea L. p. mayri (Hartert, 1930) – Arfak Mountains L. p. captus (Mayr & Gilliard, 1951) - central New Guinea L. p. insulsus (Greenway, 1935) - Herzog Mountains L. p. alberti (Rothschild & Hartert, 1907) - mountains of south-eastern New Guinea Australia L. p. clelandi (Mathews, 1911) – south-western Australia (extinct) L. p. pectoralis (Temminck, 1831) – eastern and south-eastern Australia L. p. brachipus (Swainson, 1838) – Tasmania"},{"description":"Lewin's rails are not listed as threatened on the Australian Environment Protection and Biodiversity Conservation Act 1999. However, their conservation status varies from state to state within Australia. For example: Lewin's rail is listed as threatened on the Victorian Flora and Fauna Guarantee Act (1988).Department of Sustainability and Environment, Victoria Under this Act, an Action Statement for the recovery and future management of this species has not yet been prepared.Department of Sustainability and Environment, Victoria It is also notable that the Lewin's rail is listed by an earlier scientific name (Dryolimnas pectoralis) under this Act. On the 2007 advisory list of threatened vertebrate fauna in Victoria, the Lewin's rail is listed as vulnerable. A subspecies of Lewin's rail, listed as Lewin's water rail (Rallus pectoralis clelandi), is on Western Australia's Wildlife Conservation (Specially Protected Fauna) Notice 2008 Schedule 2 — Fauna presumed to be extinct, under the WA Wildlife Conservation Act 1950. Along Kedron Brook in Brisbane, the bird is described as rare and threatened. The Brisbane Airport's construction of a second runway initially included 38 hectares of wetlands to be set aside for habitat. This was later expanded to 49 hectares to provide a more appropriate vegetation corridor. Lewin's rail is protected under the Nature Conservation Act 1992. It is an offence to damage or interfere with Lewin's rail in any other way than when accepted by the Act.Redland City Council. “Lewin's Rail.” Redland City Council, Redland City Council, 6 June 2016, www.redland.qld.gov.au/info/20254/wildlife_in_the_redlands/697/lewins_rail. Redland City Council manages environmental pests throughout the Redlands to minimize their impact on native ecosystems and birds such as Lewin's rail."},{"description":"Lewin's rail is a highly secretive bird. This species prefers permanent, fresh-to-saline wetlands surrounded by dense vegetation. That means it can be found in artificial wetlands surrounded by dense vegetation. Lewin's rails breed over the summer period, laying three to five eggs in their saucer-shaped ground nests, which they build from dry vegetation such as reeds and grasses. The nests usually sit just above the water's edge in dense reeds and grassland. These birds forage in shallow water around the water's edge, under the cover of surrounding vegetation and aquatic plants. Lewin's rails feed mainly on invertebrates and occasionally bird eggs and frogs."},{"description":"Loss of habitat due to changes in water body structure, disruption of nests, and predation by introduced species."},{"description":"South East Queensland"}],"vernacularNames":[{"vernacularName":"Lewin's rail","language":"eng"}],"synonym":false,"higherClassificationMap":{"165693667":"Lewinia"}}],"facets":[]}