{
  "scientific":"Lepomis gibbosus",
  "source":"inaturalist:worldwide",
  "common":"Pumpkinseed",
  "place":"Andalusia, Spain",
  "strategy":"location",
  "genus":"Lepomis",
  "image":"inat_49614.jpg",
  "observation":"https://www.inaturalist.org/observations/172739731",
  "variant":"loc-label",
  "family":"Centrarchidae",
  "query":"location: Andalusia, Spain",
  "overview":"",
  "strings":["My Ad Center","Andalusia","Share","Get there","Places to visit","Seville","Granada","Córdoba","Marbella","Cádiz","Ronda","Costa del Sol","Málaga","Jerez de la Frontera","Nerja","Web results","Andalusia | Spain's Southern Region, Map, & Culture","Things to do . Things to do in Andalusia","Alhambra","Royal Alcázar of Seville","Plaza de España","Mosque-Cathedral Monumental Site of Córdoba","Catedral de Sevilla","Setas de Sevilla","La Giralda","Alcazaba","Caminito del Rey . North Access","Museo Picasso Málaga","Major Cities . What are the major cities in Andalusia?","Major Cities in Andalusia","Related Links","Population . What is the population of Andalusia?","Andalusia (Spain) Population Details:","Culture . What is the culture of Andalusia?","Key Aspects of Andalusian Culture","History . What is the history of Andalusia?","Ancient History (Pre-711 CE)","The Al-Andalus Period (711–1492 CE)","Modern History (1492–Present)","Lasting Cultural Legacy","Climate . What is the climate of Andalusia?","Andalusia - Wikipedia","Geographic Location","Best Places To Visit in Andalusia For a Unique Trip in Spain","Andalusia, Spain | Political Science | Research Starters","Andalusia, Spain - Map & Guides","Videos","12 Beautiful Places To Visit In Andalusia (+ Travel Tips!) YouTube · World Wild Hearts May 18, 2024","THE Most COMPLETE Andalusia Guide! All Travel Tips & ... YouTube · Travel Tips Group Jan 26, 2026","12 Amazing places to visit in Andalusia YouTube · Expert Local Traveller Mar 12, 2025","The Geography of Andalusia - Spain","Andalucia map & highlights - Responsible Travel","Complementary Results","About","Description","Any time","Past hour","Past 24 hours","Past week","Past month","Past year","All results","Verbatim","Open in Maps","Get there $4,127+ 23h 15m to Málaga","15:47 YouTube • World Wild Hearts May 18, 2024 12 Beautiful Places To Visit In Andalusia (+ Travel Tips!)","Andalusia Wikipedia https://en.wikipedia.org › wiki › Andalusia","Read more","Andalusia | Spain's Southern Region, Map, & Culture Encyclopedia Britannica https://www.britannica.com › place › Andalusia-region-S...","More things to do","Almería","Jaén","Huelva","What are the major cities in Andalusia?","What is the population of Andalusia?","What is the culture of Andalusia?","Al-Andalus","Architecture:","Alhambra Palace","Mosque-Cathedral of Córdoba"]
}